gemini_bridge-1.2.0.dist-info/licenses/LICENSE
src/__init__.py
src/__main__.py
src/mcp_server.py
gemini_bridge-1.2.0.dist-info/METADATA
gemini_bridge-1.2.0.dist-info/WHEEL
gemini_bridge-1.2.0.dist-info/entry_points.txt
gemini_bridge-1.2.0.dist-info/top_level.txt
gemini_bridge-1.2.0.dist-info/RECORD
